adder.v
module adder(
        input_a,
        input_b,
        input_a_stb,
        input_b_stb,
        output_z_ack,
        clk,
        rst,
        output_z,
        output_z_stb,
        input_a_ack,
        input_b_ack);

  input     clk;
  input     rst;

  input     [31:0] input_a;
  input     input_a_stb;
  output    input_a_ack;

  input     [31:0] input_b;
  input     input_b_stb;
  output    input_b_ack;

  output    [31:0] output_z;
  output    output_z_stb;
  input     output_z_ack;

  reg       s_output_z_stb;
  reg       [31:0] s_output_z;
  reg       s_input_a_ack;
  reg       s_input_b_ack;

  reg       [3:0] state;
  parameter get_a         = 4'd0,
            get_b         = 4'd1,
            unpack        = 4'd2,
            special_cases = 4'd3,
            align         = 4'd4,
            add_0         = 4'd5,
            add_1         = 4'd6,
            normalise_1   = 4'd7,
            normalise_2   = 4'd8,
            round         = 4'd9,
            pack          = 4'd10,
            put_z         = 4'd11;

  reg       [31:0] a, b, z;
  reg       [26:0] a_m, b_m;
  reg       [23:0] z_m;
  reg       [9:0] a_e, b_e, z_e;
  reg       a_s, b_s, z_s;
  reg       guard, round_bit, sticky;
  reg       [27:0] sum;

  always @(posedge clk)
  begin

    case(state)

      get_a:
      begin
        s_input_a_ack <= 1;
        if (s_input_a_ack && input_a_stb) begin
          a <= input_a;
          s_input_a_ack <= 0;
          state <= get_b;
        end
      end

      get_b:
      begin
        s_input_b_ack <= 1;
        if (s_input_b_ack && input_b_stb) begin
          b <= input_b;
          s_input_b_ack <= 0;
          state <= unpack;
        end
      end

      unpack:
      begin
        a_m <= {a[22 : 0], 3'd0};
        b_m <= {b[22 : 0], 3'd0};
        a_e <= a[30 : 23] - 127;
        b_e <= b[30 : 23] - 127;
        a_s <= a[31];
        b_s <= b[31];
        state <= special_cases;
      end

      special_cases:
      begin
        //if a is NaN or b is NaN return NaN 
        if ((a_e == 128 && a_m != 0) || (b_e == 128 && b_m != 0)) begin
          z[31] <= 1;
          z[30:23] <= 255;
          z[22] <= 1;
          z[21:0] <= 0;
          state <= put_z;
        //if a is inf return inf
        end else if (a_e == 128) begin
          z[31] <= a_s;
          z[30:23] <= 255;
          z[22:0] <= 0;
          //if a is inf and signs don't match return nan
          if ((b_e == 128) && (a_s != b_s)) begin
              z[31] <= b_s;
              z[30:23] <= 255;
              z[22] <= 1;
              z[21:0] <= 0;
          end
          state <= put_z;
        //if b is inf return inf
        end else if (b_e == 128) begin
          z[31] <= b_s;
          z[30:23] <= 255;
          z[22:0] <= 0;
          state <= put_z;
        //if a is zero return b
        end else if ((($signed(a_e) == -127) && (a_m == 0)) && (($signed(b_e) == -127) && (b_m == 0))) begin
          z[31] <= a_s & b_s;
          z[30:23] <= b_e[7:0] + 127;
          z[22:0] <= b_m[26:3];
          state <= put_z;
        //if a is zero return b
        end else if (($signed(a_e) == -127) && (a_m == 0)) begin
          z[31] <= b_s;
          z[30:23] <= b_e[7:0] + 127;
          z[22:0] <= b_m[26:3];
          state <= put_z;
        //if b is zero return a
        end else if (($signed(b_e) == -127) && (b_m == 0)) begin
          z[31] <= a_s;
          z[30:23] <= a_e[7:0] + 127;
          z[22:0] <= a_m[26:3];
          state <= put_z;
        end else begin
          //Denormalised Number
          if ($signed(a_e) == -127) begin
            a_e <= -126;
          end else begin
            a_m[26] <= 1;
          end
          //Denormalised Number
          if ($signed(b_e) == -127) begin
            b_e <= -126;
          end else begin
            b_m[26] <= 1;
          end
          state <= align;
        end
      end

      align:
      begin
        if ($signed(a_e) > $signed(b_e)) begin
          b_e <= b_e + 1;
          b_m <= b_m >> 1;
          b_m[0] <= b_m[0] | b_m[1];
        end else if ($signed(a_e) < $signed(b_e)) begin
          a_e <= a_e + 1;
          a_m <= a_m >> 1;
          a_m[0] <= a_m[0] | a_m[1];
        end else begin
          state <= add_0;
        end
      end

      add_0:
      begin
        z_e <= a_e;
        if (a_s == b_s) begin
          sum <= a_m + b_m;
          z_s <= a_s;
        end else begin
          if (a_m >= b_m) begin
            sum <= a_m - b_m;
            z_s <= a_s;
          end else begin
            sum <= b_m - a_m;
            z_s <= b_s;
          end
        end
        state <= add_1;
      end

      add_1:
      begin
        if (sum[27]) begin
          z_m <= sum[27:4];
          guard <= sum[3];
          round_bit <= sum[2];
          sticky <= sum[1] | sum[0];
          z_e <= z_e + 1;
        end else begin
          z_m <= sum[26:3];
          guard <= sum[2];
          round_bit <= sum[1];
          sticky <= sum[0];
        end
        state <= normalise_1;
      end

      normalise_1:
      begin
        if (z_m[23] == 0 && $signed(z_e) > -126) begin
          z_e <= z_e - 1;
          z_m <= z_m << 1;
          z_m[0] <= guard;
          guard <= round_bit;
          round_bit <= 0;
        end else begin
          state <= normalise_2;
        end
      end

      normalise_2:
      begin
        if ($signed(z_e) < -126) begin
          z_e <= z_e + 1;
          z_m <= z_m >> 1;
          guard <= z_m[0];
          round_bit <= guard;
          sticky <= sticky | round_bit;
        end else begin
          state <= round;
        end
      end

      round:
      begin
        if (guard && (round_bit | sticky | z_m[0])) begin
          z_m <= z_m + 1;
          if (z_m == 24'hffffff) begin
            z_e <=z_e + 1;
          end
        end
        state <= pack;
      end

      pack:
      begin
        z[22 : 0] <= z_m[22:0];
        z[30 : 23] <= z_e[7:0] + 127;
        z[31] <= z_s;
        if ($signed(z_e) == -126 && z_m[23] == 0) begin
          z[30 : 23] <= 0;
        end
        if ($signed(z_e) == -126 && z_m[23:0] == 24'h0) begin
          z[31] <= 1'b0; // FIX SIGN BUG: -a + a = +0.
        end
        //if overflow occurs, return inf
        if ($signed(z_e) > 127) begin
          z[22 : 0] <= 0;
          z[30 : 23] <= 255;
          z[31] <= z_s;
        end
        state <= put_z;
      end

      put_z:
      begin
        s_output_z_stb <= 1;
        s_output_z <= z;
        if (s_output_z_stb && output_z_ack) begin
          s_output_z_stb <= 0;
          state <= get_a;
        end
      end

    endcase

    if (rst == 0) begin
      state <= get_a;
      s_input_a_ack <= 0;
      s_input_b_ack <= 0;
      s_output_z_stb <= 0;
    end

  end
  assign input_a_ack = s_input_a_ack;
  assign input_b_ack = s_input_b_ack;
  assign output_z_stb = s_output_z_stb;
  assign output_z = s_output_z;

endmodule

matrix_adder.v
module matrix_adder #(
    parameter k = 2
) (
    input [k * k * 32 - 1:0] i1matrix,
    input [k * k * 32 - 1:0] i2matrix,
    input clk,
    input resetN,
    input load,
    input result_ack,
    output [k * k * 32 - 1:0] omatrix,
    output [k * k - 1:0] result_ready
);

    wire [31:0] i1matrix_inner [0:k - 1][0:k - 1];
    wire [31:0] i2matrix_inner [0:k - 1][0:k - 1];
    wire [31:0] omatrix_inner [0:k - 1][0:k - 1];
    wire result_ready_inner [0:k - 1][0:k - 1];
    wire mat1_ack [0:k - 1][0:k - 1];
    wire mat2_ack [0:k - 1][0:k - 1];

    genvar i, j;
    generate
        for (i = 0; i < k; i = i + 1) begin
            for (j = 0; j < k; j = j + 1) begin
                assign i1matrix_inner[i][j] = i1matrix[(i * k + j + 1) * 32 - 1:(i * k + j) * 32];
                assign i2matrix_inner[i][j] = i2matrix[(i * k + j + 1) * 32 - 1:(i * k + j) * 32];
                assign omatrix[(i * k + j + 1) * 32 - 1:(i * k + j) * 32] = omatrix_inner[i][j];
                assign result_ready[i * k + j] = result_ready_inner[i][j];
            end
        end
        for (i = 0; i < k; i = i + 1) begin
            for (j = 0; j < k; j = j + 1) begin
                adder a(
                    .clk(clk),
                    .rst(resetN), 
                    .input_a(i1matrix_inner[i][j]), 
                    .input_b(i2matrix_inner[i][j]),
                    .output_z_ack(result_ack),
                    .output_z(omatrix_inner[i][j]),
                    .output_z_stb(result_ready_inner[i][j]),
                    .input_a_stb(load),
                    .input_a_ack(mat1_ack[i][j]),
                    .input_b_stb(load),
                    .input_b_ack(mat2_ack[i][j])
                );
            end
        end
    endgenerate
endmodule

matadd_tb.v
`timescale 1ns / 1ns
module matadd_tb #(parameter k = 2);
    reg [0:k - 1][0:k - 1][31:0] i1matrix;
    reg [0:k - 1][0:k - 1][31:0] i2matrix;
    reg clk, load, resetN, result_ack;
    wire [0:k - 1][0:k - 1][31:0] omatrix;
    wire [0:k - 1][0:k - 1] result_ready;

    matrix_adder #(.k(k)) mult(
        .i1matrix(i1matrix),
        .i2matrix(i2matrix),
        .omatrix(omatrix),
        .result_ready(result_ready),
        .result_ack(result_ack),
        .load(load),
        .resetN(resetN),
        .clk(clk)
    );
    
    // genvar i;
    // generate
    //     for (i = 0; i < k * k; i = i + 1) begin
    //         adder a(
    //             .clk(clk),
    //             .reset(resetN), 
    //             .load(load),
    //             .Number1(i1matrix[i / k][i % k]), 
    //             .Number2(i2matrix[i / k][i % k]),
    //             .result_ack(result_ack),
    //             .Result(omatrix[i / k][i % k]),
    //             .result_ready(result_ready[i])
    //         );
    //     end
    // endgenerate

    initial begin
        clk = 0;
        forever begin
            #5 clk = ~clk;
        end
    end

    initial begin
        $dumpfile("add.vcd");
        $dumpvars(0, matadd_tb);
        resetN = 0;
        #100
        load = 1;
        resetN = 1;
        i1matrix[0][0] = 32'h40A00000;
        i1matrix[0][1] = 32'b00111111100000000000000000000001;
        i1matrix[1][0] = 32'b00111111100000000000000000000010;
        i1matrix[1][1] = 32'b00111111100000000000000000000100;

        i2matrix[0][0] = 32'h00000000;
        i2matrix[0][1] = 32'b00111111100000000000000000000111;
        i2matrix[1][0] = 32'b00111111100000000000000000000100;
        i2matrix[1][1] = 32'b00111111100000000000000000000100;

        result_ack = 0;
        
        #1000 $finish;
    end
endmodule

add.vcd
$date
	Sun Jul 11 17:23:05 2021
$end
$version
	Icarus Verilog
$end
$timescale
	1ns
$end
$scope module matadd_tb $end
$var wire 4 ! result_ready [3:0] $end
$var wire 128 " omatrix [127:0] $end
$var reg 1 # clk $end
$var reg 128 $ i1matrix [127:0] $end
$var reg 128 % i2matrix [127:0] $end
$var reg 1 & load $end
$var reg 1 ' resetN $end
$var reg 1 ( result_ack $end
$scope module mult $end
$var wire 1 # clk $end
$var wire 128 ) i1matrix [127:0] $end
$var wire 128 * i2matrix [127:0] $end
$var wire 1 & load $end
$var wire 1 ' resetN $end
$var wire 1 ( result_ack $end
$var wire 4 + result_ready [3:0] $end
$var wire 128 , omatrix [127:0] $end
$scope begin genblk1[0] $end
$scope begin genblk2[0] $end
$upscope $end
$scope begin genblk2[1] $end
$upscope $end
$upscope $end
$scope begin genblk1[1] $end
$scope begin genblk2[0] $end
$upscope $end
$scope begin genblk2[1] $end
$upscope $end
$upscope $end
$scope begin genblk3[0] $end
$scope begin genblk4[0] $end
$scope module a $end
$var wire 1 # clk $end
$var wire 32 - input_a [31:0] $end
$var wire 1 . input_a_ack $end
$var wire 1 & input_a_stb $end
$var wire 32 / input_b [31:0] $end
$var wire 1 0 input_b_ack $end
$var wire 1 & input_b_stb $end
$var wire 1 ( output_z_ack $end
$var wire 1 ' rst $end
$var wire 1 1 output_z_stb $end
$var wire 32 2 output_z [31:0] $end
$var reg 32 3 a [31:0] $end
$var reg 10 4 a_e [9:0] $end
$var reg 27 5 a_m [26:0] $end
$var reg 1 6 a_s $end
$var reg 32 7 b [31:0] $end
$var reg 10 8 b_e [9:0] $end
$var reg 27 9 b_m [26:0] $end
$var reg 1 : b_s $end
$var reg 1 ; guard $end
$var reg 1 < round_bit $end
$var reg 1 = s_input_a_ack $end
$var reg 1 > s_input_b_ack $end
$var reg 32 ? s_output_z [31:0] $end
$var reg 1 1 s_output_z_stb $end
$var reg 4 @ state [3:0] $end
$var reg 1 A sticky $end
$var reg 28 B sum [27:0] $end
$var reg 32 C z [31:0] $end
$var reg 10 D z_e [9:0] $end
$var reg 24 E z_m [23:0] $end
$var reg 1 F z_s $end
$upscope $end
$upscope $end
$scope begin genblk4[1] $end
$scope module a $end
$var wire 1 # clk $end
$var wire 32 G input_a [31:0] $end
$var wire 1 H input_a_ack $end
$var wire 1 & input_a_stb $end
$var wire 32 I input_b [31:0] $end
$var wire 1 J input_b_ack $end
$var wire 1 & input_b_stb $end
$var wire 1 ( output_z_ack $end
$var wire 1 ' rst $end
$var wire 1 K output_z_stb $end
$var wire 32 L output_z [31:0] $end
$var reg 32 M a [31:0] $end
$var reg 10 N a_e [9:0] $end
$var reg 27 O a_m [26:0] $end
$var reg 1 P a_s $end
$var reg 32 Q b [31:0] $end
$var reg 10 R b_e [9:0] $end
$var reg 27 S b_m [26:0] $end
$var reg 1 T b_s $end
$var reg 1 U guard $end
$var reg 1 V round_bit $end
$var reg 1 W s_input_a_ack $end
$var reg 1 X s_input_b_ack $end
$var reg 32 Y s_output_z [31:0] $end
$var reg 1 K s_output_z_stb $end
$var reg 4 Z state [3:0] $end
$var reg 1 [ sticky $end
$var reg 28 \ sum [27:0] $end
$var reg 32 ] z [31:0] $end
$var reg 10 ^ z_e [9:0] $end
$var reg 24 _ z_m [23:0] $end
$var reg 1 ` z_s $end
$upscope $end
$upscope $end
$upscope $end
$scope begin genblk3[1] $end
$scope begin genblk4[0] $end
$scope module a $end
$var wire 1 # clk $end
$var wire 32 a input_a [31:0] $end
$var wire 1 b input_a_ack $end
$var wire 1 & input_a_stb $end
$var wire 32 c input_b [31:0] $end
$var wire 1 d input_b_ack $end
$var wire 1 & input_b_stb $end
$var wire 1 ( output_z_ack $end
$var wire 1 ' rst $end
$var wire 1 e output_z_stb $end
$var wire 32 f output_z [31:0] $end
$var reg 32 g a [31:0] $end
$var reg 10 h a_e [9:0] $end
$var reg 27 i a_m [26:0] $end
$var reg 1 j a_s $end
$var reg 32 k b [31:0] $end
$var reg 10 l b_e [9:0] $end
$var reg 27 m b_m [26:0] $end
$var reg 1 n b_s $end
$var reg 1 o guard $end
$var reg 1 p round_bit $end
$var reg 1 q s_input_a_ack $end
$var reg 1 r s_input_b_ack $end
$var reg 32 s s_output_z [31:0] $end
$var reg 1 e s_output_z_stb $end
$var reg 4 t state [3:0] $end
$var reg 1 u sticky $end
$var reg 28 v sum [27:0] $end
$var reg 32 w z [31:0] $end
$var reg 10 x z_e [9:0] $end
$var reg 24 y z_m [23:0] $end
$var reg 1 z z_s $end
$upscope $end
$upscope $end
$scope begin genblk4[1] $end
$scope module a $end
$var wire 1 # clk $end
$var wire 32 { input_a [31:0] $end
$var wire 1 | input_a_ack $end
$var wire 1 & input_a_stb $end
$var wire 32 } input_b [31:0] $end
$var wire 1 ~ input_b_ack $end
$var wire 1 & input_b_stb $end
$var wire 1 ( output_z_ack $end
$var wire 1 ' rst $end
$var wire 1 !" output_z_stb $end
$var wire 32 "" output_z [31:0] $end
$var reg 32 #" a [31:0] $end
$var reg 10 $" a_e [9:0] $end
$var reg 27 %" a_m [26:0] $end
$var reg 1 &" a_s $end
$var reg 32 '" b [31:0] $end
$var reg 10 (" b_e [9:0] $end
$var reg 27 )" b_m [26:0] $end
$var reg 1 *" b_s $end
$var reg 1 +" guard $end
$var reg 1 ," round_bit $end
$var reg 1 -" s_input_a_ack $end
$var reg 1 ." s_input_b_ack $end
$var reg 32 /" s_output_z [31:0] $end
$var reg 1 !" s_output_z_stb $end
$var reg 4 0" state [3:0] $end
$var reg 1 1" sticky $end
$var reg 28 2" sum [27:0] $end
$var reg 32 3" z [31:0] $end
$var reg 10 4" z_e [9:0] $end
$var reg 24 5" z_m [23:0] $end
$var reg 1 6" z_s $end
$upscope $end
$upscope $end
$upscope $end
$upscope $end
$upscope $end
$enddefinitions $end
#0
$dumpvars
x6"
bx 5"
bx 4"
bx 3"
bx 2"
x1"
bx 0"
bx /"
x."
x-"
x,"
x+"
x*"
bx )"
bx ("
bx '"
x&"
bx %"
bx $"
bx #"
bx ""
x!"
x~
bx }
x|
bx {
xz
bx y
bx x
bx w
bx v
xu
bx t
bx s
xr
xq
xp
xo
xn
bx m
bx l
bx k
xj
bx i
bx h
bx g
bx f
xe
xd
bx c
xb
bx a
x`
bx _
bx ^
bx ]
bx \
x[
bx Z
bx Y
xX
xW
xV
xU
xT
bx S
bx R
bx Q
xP
bx O
bx N
bx M
bx L
xK
xJ
bx I
xH
bx G
xF
bx E
bx D
bx C
bx B
xA
bx @
bx ?
x>
x=
x<
x;
x:
bx 9
bx 8
bx 7
x6
bx 5
bx 4
bx 3
bx 2
x1
x0
bx /
x.
bx -
bx ,
bx +
bx *
bx )
x(
0'
x&
bx %
bx $
0#
bx "
bx !
$end
#5
01
00
0>
0.
0=
b0 @
0K
0J
0X
0H
0W
b0 Z
0e
0d
0r
0b
0q
b0 t
b0 !
b0 +
0!"
0~
0."
0|
0-"
b0 0"
1#
#10
0#
#15
0|
0-"
0b
0q
0H
0W
0.
0=
1#
#20
0#
#25
0.
0=
0H
0W
0b
0q
0|
0-"
1#
#30
0#
#35
0|
0-"
0b
0q
0H
0W
0.
0=
1#
#40
0#
#45
0.
0=
0H
0W
0b
0q
0|
0-"
1#
#50
0#
#55
0|
0-"
0b
0q
0H
0W
0.
0=
1#
#60
0#
#65
0.
0=
0H
0W
0b
0q
0|
0-"
1#
#70
0#
#75
0|
0-"
0b
0q
0H
0W
0.
0=
1#
#80
0#
#85
0.
0=
0H
0W
0b
0q
0|
0-"
1#
#90
0#
#95
0|
0-"
0b
0q
0H
0W
0.
0=
1#
#100
b111111100000000000000000000100 /
b111111100000000000000000000100 I
b111111100000000000000000000111 c
b0 }
b111111100000000000000000000100 -
b111111100000000000000000000010 G
b111111100000000000000000000001 a
b1000000101000000000000000000000 {
0#
0(
b1111111000000000000000000001110011111110000000000000000000010000111111100000000000000000000100 %
b1111111000000000000000000001110011111110000000000000000000010000111111100000000000000000000100 *
b1000000101000000000000000000000001111111000000000000000000000010011111110000000000000000000001000111111100000000000000000000100 $
b1000000101000000000000000000000001111111000000000000000000000010011111110000000000000000000001000111111100000000000000000000100 )
1'
1&
#105
1.
1=
1H
1W
1b
1q
1|
1-"
1#
#110
0#
#115
b1 0"
0|
0-"
b1000000101000000000000000000000 #"
b1 t
0b
0q
b111111100000000000000000000001 g
b1 Z
0H
0W
b111111100000000000000000000010 M
b1 @
0.
0=
b111111100000000000000000000100 3
1#
#120
0#
#125
10
1>
1J
1X
1d
1r
1~
1."
1#
#130
0#
#135
b10 0"
0~
0."
b0 '"
b10 t
0d
0r
b111111100000000000000000000111 k
b10 Z
0J
0X
b111111100000000000000000000100 Q
b10 @
00
0>
b111111100000000000000000000100 7
1#
#140
0#
#145
b11 @
0:
06
b0 8
b0 4
b100000 9
b100000 5
b11 Z
0T
0P
b0 R
b0 N
b100000 S
b10000 O
b11 t
0n
0j
b0 l
b0 h
b111000 m
b1000 i
b11 0"
0*"
0&"
b1110000001 ("
b10 $"
b0 )"
b1000000000000000000000000 %"
1#
#150
0#
#155
b1011 0"
b1000000101000000000000000000000 3"
b100 t
b100000000000000000000111000 m
b100000000000000000000001000 i
b100 Z
b100000000000000000000100000 S
b100000000000000000000010000 O
b100 @
b100000000000000000000100000 9
b100000000000000000000100000 5
1#
#160
0#
#165
b101 @
b101 Z
b101 t
b1000000101000000000000000000000xxxxxxxxxxxxxxxxxxxxxxxxxxxxxxxxxxxxxxxxxxxxxxxxxxxxxxxxxxxxxxxxxxxxxxxxxxxxxxxxxxxxxxxxxxxxxxxx "
b1000000101000000000000000000000xxxxxxxxxxxxxxxxxxxxxxxxxxxxxxxxxxxxxxxxxxxxxxxxxxxxxxxxxxxxxxxxxxxxxxxxxxxxxxxxxxxxxxxxxxxxxxxx ,
b1000000101000000000000000000000 ""
b1000000101000000000000000000000 /"
b1000 !
b1000 +
1!"
1#
#170
0#
#175
b110 t
0z
b1000000000000000000001000000 v
b0 x
b110 Z
0`
b1000000000000000000000110000 \
b0 ^
b110 @
0F
b1000000000000000000001000000 B
b0 D
1#
#180
0#
#185
b111 @
b1 D
0A
0<
0;
b100000000000000000000100 E
b111 Z
b1 ^
0[
0V
0U
b100000000000000000000011 _
b111 t
b1 x
0u
0p
0o
b100000000000000000000100 y
1#
#190
0#
#195
b1000 t
b1000 Z
b1000 @
1#
#200
0#
#205
b1001 @
b1001 Z
b1001 t
1#
#210
0#
#215
b1010 t
b1010 Z
b1010 @
1#
#220
0#
#225
b1011 @
b1000000000000000000000000000100 C
b1011 Z
b1000000000000000000000000000011 ]
b1011 t
b1000000000000000000000000000100 w
1#
#230
0#
#235
b1000000000000000000000000000100 f
b1000000000000000000000000000100 s
1e
b1000000000000000000000000000011 L
b1000000000000000000000000000011 Y
1K
b1000000101000000000000000000000010000000000000000000000000001000100000000000000000000000000001101000000000000000000000000000100 "
b1000000101000000000000000000000010000000000000000000000000001000100000000000000000000000000001101000000000000000000000000000100 ,
b1000000000000000000000000000100 2
b1000000000000000000000000000100 ?
b1111 !
b1111 +
11
1#
