single_multiplier.v
//IEEE Floating Point Multiplier (Single Precision)
//Copyright (C) Jonathan P Dawson 2013
//2013-12-12
module single_multiplier(
        input_a,
        input_b,
        input_a_stb,
        input_b_stb,
        output_z_ack,
        clk,
        rst,
        output_z,
        output_z_stb,
        input_a_ack,
        input_b_ack);

  input     clk;
  input     rst;

  input     [31:0] input_a;
  input     input_a_stb;
  output    input_a_ack;

  input     [31:0] input_b;
  input     input_b_stb;
  output    input_b_ack;

  output    [31:0] output_z;
  output    output_z_stb;
  input     output_z_ack;

  reg       s_output_z_stb;
  reg       [31:0] s_output_z;
  reg       s_input_a_ack;
  reg       s_input_b_ack;

  reg       [3:0] state;
  parameter get_a         = 4'd0,
            get_b         = 4'd1,
            unpack        = 4'd2,
            special_cases = 4'd3,
            normalise_a   = 4'd4,
            normalise_b   = 4'd5,
            multiply_0    = 4'd6,
            multiply_1    = 4'd7,
            normalise_1   = 4'd8,
            normalise_2   = 4'd9,
            round         = 4'd10,
            pack          = 4'd11,
            put_z         = 4'd12;

  reg       [31:0] a, b, z;
  reg       [23:0] a_m, b_m, z_m;
  reg       [9:0] a_e, b_e, z_e;
  reg       a_s, b_s, z_s;
  reg       guard, round_bit, sticky;
  reg       [49:0] product;

  always @(posedge clk or negedge rst)
  begin

    case(state)

      get_a:
      begin
        s_input_a_ack <= 1;
        if (s_input_a_ack && input_a_stb) begin
          a <= input_a;
          s_input_a_ack <= 0;
          state <= get_b;
        end
      end

      get_b:
      begin
        s_input_b_ack <= 1;
        if (s_input_b_ack && input_b_stb) begin
          b <= input_b;
          s_input_b_ack <= 0;
          state <= unpack;
        end
      end

      unpack:
      begin
        a_m <= a[22 : 0];
        b_m <= b[22 : 0];
        a_e <= a[30 : 23] - 127;
        b_e <= b[30 : 23] - 127;
        a_s <= a[31];
        b_s <= b[31];
        state <= special_cases;
      end

      special_cases:
      begin
        //if a is NaN or b is NaN return NaN 
        if ((a_e == 128 && a_m != 0) || (b_e == 128 && b_m != 0)) begin
          z[31] <= 1;
          z[30:23] <= 255;
          z[22] <= 1;
          z[21:0] <= 0;
          state <= put_z;
        //if a is inf return inf
        end else if (a_e == 128) begin
          z[31] <= a_s ^ b_s;
          z[30:23] <= 255;
          z[22:0] <= 0;
          //if b is zero return NaN
          if (($signed(b_e) == -127) && (b_m == 0)) begin
            z[31] <= 1;
            z[30:23] <= 255;
            z[22] <= 1;
            z[21:0] <= 0;
          end
          state <= put_z;
        //if b is inf return inf
        end else if (b_e == 128) begin
          z[31] <= a_s ^ b_s;
          z[30:23] <= 255;
          z[22:0] <= 0;
          //if a is zero return NaN
          if (($signed(a_e) == -127) && (a_m == 0)) begin
            z[31] <= 1;
            z[30:23] <= 255;
            z[22] <= 1;
            z[21:0] <= 0;
          end
          state <= put_z;
        //if a is zero return zero
        end else if (($signed(a_e) == -127) && (a_m == 0)) begin
          z[31] <= a_s ^ b_s;
          z[30:23] <= 0;
          z[22:0] <= 0;
          state <= put_z;
        //if b is zero return zero
        end else if (($signed(b_e) == -127) && (b_m == 0)) begin
          z[31] <= a_s ^ b_s;
          z[30:23] <= 0;
          z[22:0] <= 0;
          state <= put_z;
        end else begin
          //Denormalised Number
          if ($signed(a_e) == -127) begin
            a_e <= -126;
          end else begin
            a_m[23] <= 1;
          end
          //Denormalised Number
          if ($signed(b_e) == -127) begin
            b_e <= -126;
          end else begin
            b_m[23] <= 1;
          end
          state <= normalise_a;
        end
      end

      normalise_a:
      begin
        if (a_m[23]) begin
          state <= normalise_b;
        end else begin
          a_m <= a_m << 1;
          a_e <= a_e - 1;
        end
      end

      normalise_b:
      begin
        if (b_m[23]) begin
          state <= multiply_0;
        end else begin
          b_m <= b_m << 1;
          b_e <= b_e - 1;
        end
      end

      multiply_0:
      begin
        z_s <= a_s ^ b_s;
        z_e <= a_e + b_e + 1;
        product <= a_m * b_m * 4;
        state <= multiply_1;
      end

      multiply_1:
      begin
        z_m <= product[49:26];
        guard <= product[25];
        round_bit <= product[24];
        sticky <= (product[23:0] != 0);
        state <= normalise_1;
      end

      normalise_1:
      begin
        if (z_m[23] == 0) begin
          z_e <= z_e - 1;
          z_m <= z_m << 1;
          z_m[0] <= guard;
          guard <= round_bit;
          round_bit <= 0;
        end else begin
          state <= normalise_2;
        end
      end

      normalise_2:
      begin
        if ($signed(z_e) < -126) begin
          z_e <= z_e + 1;
          z_m <= z_m >> 1;
          guard <= z_m[0];
          round_bit <= guard;
          sticky <= sticky | round_bit;
        end else begin
          state <= round;
        end
      end

      round:
      begin
        if (guard && (round_bit | sticky | z_m[0])) begin
          z_m <= z_m + 1;
          if (z_m == 24'hffffff) begin
            z_e <=z_e + 1;
          end
        end
        state <= pack;
      end

      pack:
      begin
        z[22 : 0] <= z_m[22:0];
        z[30 : 23] <= z_e[7:0] + 127;
        z[31] <= z_s;
        if ($signed(z_e) == -126 && z_m[23] == 0) begin
          z[30 : 23] <= 0;
        end
        //if overflow occurs, return inf
        if ($signed(z_e) > 127) begin
          z[22 : 0] <= 0;
          z[30 : 23] <= 255;
          z[31] <= z_s;
        end
        state <= put_z;
      end

      put_z:
      begin
        s_output_z_stb <= 1;
        s_output_z <= z;
        if (s_output_z_stb && output_z_ack) begin
          s_output_z_stb <= 0;
          state <= get_a;
        end
      end

    endcase

    if (rst == 0) begin
      state <= get_a;
      s_input_a_ack <= 0;
      s_input_b_ack <= 0;
      s_output_z_stb <= 0;
    end

  end
  assign input_a_ack = s_input_a_ack;
  assign input_b_ack = s_input_b_ack;
  assign output_z_stb = s_output_z_stb;
  assign output_z = s_output_z;

endmodule

matrix_multiplier.v
module matrix_multiplier #(
    parameter k = 2
) (
    input [k * k * 32 - 1:0] i1matrix,
    input [k * k * 32 - 1:0] i2matrix,
    input matrix1_ready,
    input matrix2_ready,
    input clk,
    input resetN,
    input result_ack,
    output [k * k * 32 - 1:0] omatrix,
    output [k * k - 1:0] result_ready
);
    wire [k * 32 - 1:0] medmatrix [0:k - 1][0:k - 1];
    wire [k - 1:0] medmult_ready [0:k - 1][0:k - 1];
    wire [k - 1:0] mat1_ack [0:k - 1][0:k - 1];
    wire [k - 1:0] mat2_ack [0:k - 1][0:k - 1];

    wire [31:0] i1matrix_inner [0:k - 1][0:k - 1];
    wire [31:0] i2matrix_inner [0:k - 1][0:k - 1];
    wire [31:0] omatrix_inner [0:k - 1][0:k - 1];
    wire result_ready_inner [0:k - 1][0:k - 1];

    genvar i, j, p;
    generate
        for (i = 0; i < k; i = i + 1) begin
            for (j = 0; j < k; j = j + 1) begin
                assign i1matrix_inner[i][j] = i1matrix[(i * k + j + 1) * 32 - 1:(i * k + j) * 32];
                assign i2matrix_inner[i][j] = i2matrix[(i * k + j + 1) * 32 - 1:(i * k + j) * 32];
                assign omatrix[(i * k + j + 1) * 32 - 1:(i * k + j) * 32] = omatrix_inner[i][j];
                assign result_ready[i * k + j] = result_ready_inner[i][j];
            end
        end
        for (i = 0; i < k; i = i + 1) begin
            for (j = 0; j < k; j = j + 1) begin
                for (p = 0; p < k; p = p + 1) begin
                    single_multiplier m(
                        .clk(clk),
                        .rst(resetN),
                        .input_a(i1matrix_inner[i][p]),
                        .input_b(i2matrix_inner[p][j]),
                        .output_z(medmatrix[i][j][(p + 1) * 32 - 1: p * 32]),
                        .input_a_stb(matrix1_ready),
                        .input_b_stb(matrix2_ready),
                        .input_a_ack(mat1_ack[i][j][p]),
                        .input_b_ack(mat2_ack[i][j][p]),
                        .output_z_stb(medmult_ready[i][j][p]),
                        .output_z_ack(result_ack)
                    );
                end
                vector_add_reduce #(.k(k)) var (
                    .vector(medmatrix[i][j]),
                    .clk(clk),
                    .resetN(resetN),
                    .data_in_ready(medmult_ready[i][j]),
                    .data_out_ack(result_ack),
                    .result(omatrix_inner[i][j]),
                    .data_out_ready(result_ready_inner[i][j])
                );
            end
        end
    endgenerate
endmodule

matmul_tb.v
`timescale 1ns / 1ns
module matmul_tb #(parameter k = 1);
    reg [0:k - 1][0:k - 1][31:0] i1matrix;
    reg [0:k - 1][0:k - 1][31:0] i2matrix;
    reg matrix1_ready;
    reg matrix2_ready;
    reg clk, resetN, result_ack;
    wire [0:k - 1][0:k - 1][31:0] omatrix;
    wire [0:k - 1][0:k - 1] result_ready;

    matrix_multiplier #(.k(k)) mult(
        .i1matrix(i1matrix),
        .i2matrix(i2matrix),
        .matrix1_ready(matrix1_ready),
        .matrix2_ready(matrix2_ready),
        .omatrix(omatrix),
        .result_ready(result_ready),
        .result_ack(result_ack),
        .resetN(resetN),
        .clk(clk)
    );
    
    // genvar i, j, p;
    // generate
    //     for (i = 0; i < k; i = i + 1) begin
    //         for (j = 0; j < k; j = j + 1) begin
    //             for (p = 0; p < k; p = p + 1) begin
    //                 single_multiplier m(
    //                     .clk(clk),
    //                     .rst(resetN),
    //                     .input_a(i1matrix[i][p]),
    //                     .input_b(i2matrix[p][j]),
    //                     .output_z(medmatrix[i][j][p]),
    //                     .input_a_stb(matrix1_ready),
    //                     .input_b_stb(matrix2_ready),
    //                     .input_a_ack(mat1_ack[i][j][p]),
    //                     .input_b_ack(mat2_ack[i][j][p]),
    //                     .output_z_stb(medmult_ready[i][j][p]),
    //                     .output_z_ack(result_ack)
    //                 );
    //             end
    //             // vector_add_reduce #(.k(k)) var (
    //             //     .vector(medmatrix[i][j]),
    //             //     .clk(clk),
    //             //     .resetN(resetN),
    //             //     .data_in_ready(&medmult_ready[i][j]),
    //             //     .data_out_ack(result_ack),
    //             //     .result(omatrix[i][j]),
    //             //     .data_out_ready(result_ready[i][j])
    //             // );
    //         end
    //     end
    // endgenerate
    
    // genvar i;
    // generate
    //     for (i = 0; i < k * k; i = i + 1) begin
    //         adder a(
    //             .clk(clk),
    //             .reset(resetN), 
    //             .load(load),
    //             .Number1(i1matrix[i / k][i % k]), 
    //             .Number2(i2matrix[i / k][i % k]),
    //             .result_ack(result_ack),
    //             .Result(omatrix[i / k][i % k]),
    //             .result_ready(result_ready[i])
    //         );
    //     end
    // endgenerate

    initial begin
        clk = 0;
        forever begin
            #5 clk = ~clk;
        end
    end

    initial begin
        $dumpfile("mult.vcd");
        $dumpvars(0, matmul_tb);
        resetN = 1;
        #10resetN = 0;
        i1matrix[0][0] = 0;
        i2matrix[0][0] = 0;
        matrix1_ready = 0;
        matrix2_ready = 0;
        #1000
        resetN = 1;
        i1matrix[0][0] = 32'h3f800000;
        // i1matrix[0][1] = 32'b00111111100000000000000000000001;
        // i1matrix[1][0] = 32'b00111111100000000000000000000010;
        // i1matrix[1][1] = 32'b00111111100000000000000000000100;

        i2matrix[0][0] = 32'h40A00000;
        // i2matrix[0][1] = 32'b00111111100000000000000000000010;
        // i2matrix[1][0] = 32'b00111111100000000000000000000100;
        // i2matrix[1][1] = 32'b00111111100000000000000000000100;

        #10;
        matrix1_ready = 1;
        matrix2_ready = 1;

        result_ack = 0;
        
        #5000 $finish;
    end
endmodule

mult.vcd
$date
	Sun Jul 11 17:37:59 2021
$end
$version
	Icarus Verilog
$end
$timescale
	1ns
$end
$scope module matmul_tb $end
$var wire 1 ! result_ready $end
$var wire 32 " omatrix [31:0] $end
$var reg 1 # clk $end
$var reg 32 $ i1matrix [31:0] $end
$var reg 32 % i2matrix [31:0] $end
$var reg 1 & matrix1_ready $end
$var reg 1 ' matrix2_ready $end
$var reg 1 ( resetN $end
$var reg 1 ) result_ack $end
$scope module mult $end
$var wire 1 # clk $end
$var wire 32 * i1matrix [31:0] $end
$var wire 32 + i2matrix [31:0] $end
$var wire 1 & matrix1_ready $end
$var wire 1 ' matrix2_ready $end
$var wire 1 ( resetN $end
$var wire 1 ) result_ack $end
$var wire 1 ! result_ready $end
$var wire 32 , omatrix [31:0] $end
$scope begin genblk1[0] $end
$scope begin genblk2[0] $end
$upscope $end
$upscope $end
$scope begin genblk3[0] $end
$scope begin genblk4[0] $end
$scope begin genblk5[0] $end
$scope module m $end
$var wire 1 # clk $end
$var wire 32 - input_a [31:0] $end
$var wire 1 . input_a_ack $end
$var wire 1 & input_a_stb $end
$var wire 32 / input_b [31:0] $end
$var wire 1 0 input_b_ack $end
$var wire 1 ' input_b_stb $end
$var wire 1 ) output_z_ack $end
$var wire 1 ( rst $end
$var wire 1 1 output_z_stb $end
$var wire 32 2 output_z [31:0] $end
$var reg 32 3 a [31:0] $end
$var reg 10 4 a_e [9:0] $end
$var reg 24 5 a_m [23:0] $end
$var reg 1 6 a_s $end
$var reg 32 7 b [31:0] $end
$var reg 10 8 b_e [9:0] $end
$var reg 24 9 b_m [23:0] $end
$var reg 1 : b_s $end
$var reg 1 ; guard $end
$var reg 50 < product [49:0] $end
$var reg 1 = round_bit $end
$var reg 1 > s_input_a_ack $end
$var reg 1 ? s_input_b_ack $end
$var reg 32 @ s_output_z [31:0] $end
$var reg 1 1 s_output_z_stb $end
$var reg 4 A state [3:0] $end
$var reg 1 B sticky $end
$var reg 32 C z [31:0] $end
$var reg 10 D z_e [9:0] $end
$var reg 24 E z_m [23:0] $end
$var reg 1 F z_s $end
$upscope $end
$upscope $end
$scope module var $end
$var wire 1 # clk $end
$var wire 1 1 data_in_ready $end
$var wire 1 ) data_out_ack $end
$var wire 1 ( resetN $end
$var wire 32 G vector [31:0] $end
$var wire 32 H result [31:0] $end
$var wire 1 I data_out_ready $end
$scope begin genblk1[0] $end
$upscope $end
$scope begin genblk4 $end
$upscope $end
$upscope $end
$upscope $end
$upscope $end
$upscope $end
$upscope $end
$enddefinitions $end
#0
$dumpvars
xI
bx H
bx G
xF
bx E
bx D
bx C
xB
bx A
bx @
x?
x>
x=
bx <
x;
x:
bx 9
bx 8
bx 7
x6
bx 5
bx 4
bx 3
bx 2
x1
x0
bx /
x.
bx -
bx ,
bx +
bx *
x)
1(
x'
x&
bx %
bx $
0#
bx "
x!
$end
#5
1#
#10
0!
0I
01
00
0?
0.
0>
b0 A
0#
0'
0&
b0 /
b0 %
b0 +
b0 -
b0 $
b0 *
0(
#15
0.
0>
1#
#20
0#
#25
0.
0>
1#
#30
0#
#35
0.
0>
1#
#40
0#
#45
0.
0>
1#
#50
0#
#55
0.
0>
1#
#60
0#
#65
0.
0>
1#
#70
0#
#75
0.
0>
1#
#80
0#
#85
0.
0>
1#
#90
0#
#95
0.
0>
1#
#100
0#
#105
0.
0>
1#
#110
0#
#115
0.
0>
1#
#120
0#
#125
0.
0>
1#
#130
0#
#135
0.
0>
1#
#140
0#
#145
0.
0>
1#
#150
0#
#155
0.
0>
1#
#160
0#
#165
0.
0>
1#
#170
0#
#175
0.
0>
1#
#180
0#
#185
0.
0>
1#
#190
0#
#195
0.
0>
1#
#200
0#
#205
0.
0>
1#
#210
0#
#215
0.
0>
1#
#220
0#
#225
0.
0>
1#
#230
0#
#235
0.
0>
1#
#240
0#
#245
0.
0>
1#
#250
0#
#255
0.
0>
1#
#260
0#
#265
0.
0>
1#
#270
0#
#275
0.
0>
1#
#280
0#
#285
0.
0>
1#
#290
0#
#295
0.
0>
1#
#300
0#
#305
0.
0>
1#
#310
0#
#315
0.
0>
1#
#320
0#
#325
0.
0>
1#
#330
0#
#335
0.
0>
1#
#340
0#
#345
0.
0>
1#
#350
0#
#355
0.
0>
1#
#360
0#
#365
0.
0>
1#
#370
0#
#375
0.
0>
1#
#380
0#
#385
0.
0>
1#
#390
0#
#395
0.
0>
1#
#400
0#
#405
0.
0>
1#
#410
0#
#415
0.
0>
1#
#420
0#
#425
0.
0>
1#
#430
0#
#435
0.
0>
1#
#440
0#
#445
0.
0>
1#
#450
0#
#455
0.
0>
1#
#460
0#
#465
0.
0>
1#
#470
0#
#475
0.
0>
1#
#480
0#
#485
0.
0>
1#
#490
0#
#495
0.
0>
1#
#500
0#
#505
0.
0>
1#
#510
0#
#515
0.
0>
1#
#520
0#
#525
0.
0>
1#
#530
0#
#535
0.
0>
1#
#540
0#
#545
0.
0>
1#
#550
0#
#555
0.
0>
1#
#560
0#
#565
0.
0>
1#
#570
0#
#575
0.
0>
1#
#580
0#
#585
0.
0>
1#
#590
0#
#595
0.
0>
1#
#600
0#
#605
0.
0>
1#
#610
0#
#615
0.
0>
1#
#620
0#
#625
0.
0>
1#
#630
0#
#635
0.
0>
1#
#640
0#
#645
0.
0>
1#
#650
0#
#655
0.
0>
1#
#660
0#
#665
0.
0>
1#
#670
0#
#675
0.
0>
1#
#680
0#
#685
0.
0>
1#
#690
0#
#695
0.
0>
1#
#700
0#
#705
0.
0>
1#
#710
0#
#715
0.
0>
1#
#720
0#
#725
0.
0>
1#
#730
0#
#735
0.
0>
1#
#740
0#
#745
0.
0>
1#
#750
0#
#755
0.
0>
1#
#760
0#
#765
0.
0>
1#
#770
0#
#775
0.
0>
1#
#780
0#
#785
0.
0>
1#
#790
0#
#795
0.
0>
1#
#800
0#
#805
0.
0>
1#
#810
0#
#815
0.
0>
1#
#820
0#
#825
0.
0>
1#
#830
0#
#835
0.
0>
1#
#840
0#
#845
0.
0>
1#
#850
0#
#855
0.
0>
1#
#860
0#
#865
0.
0>
1#
#870
0#
#875
0.
0>
1#
#880
0#
#885
0.
0>
1#
#890
0#
#895
0.
0>
1#
#900
0#
#905
0.
0>
1#
#910
0#
#915
0.
0>
1#
#920
0#
#925
0.
0>
1#
#930
0#
#935
0.
0>
1#
#940
0#
#945
0.
0>
1#
#950
0#
#955
0.
0>
1#
#960
0#
#965
0.
0>
1#
#970
0#
#975
0.
0>
1#
#980
0#
#985
0.
0>
1#
#990
0#
#995
0.
0>
1#
#1000
0#
#1005
0.
0>
1#
#1010
0#
b1000000101000000000000000000000 /
b1000000101000000000000000000000 %
b1000000101000000000000000000000 +
b111111100000000000000000000000 -
b111111100000000000000000000000 $
b111111100000000000000000000000 *
1(
#1015
1.
1>
1#
#1020
0#
0)
1'
1&
#1025
b1 A
0.
0>
b111111100000000000000000000000 3
1#
#1030
0#
#1035
10
1?
1#
#1040
0#
#1045
b10 A
00
0?
b1000000101000000000000000000000 7
1#
#1050
0#
#1055
b11 A
0:
06
b10 8
b0 4
b1000000000000000000000 9
b0 5
1#
#1060
0#
#1065
b100 A
b101000000000000000000000 9
b100000000000000000000000 5
1#
#1070
0#
#1075
b101 A
1#
#1080
0#
#1085
b110 A
1#
#1090
0#
#1095
b111 A
b1010000000000000000000000000000000000000000000000 <
b11 D
0F
1#
#1100
0#
#1105
b1000 A
0B
0=
0;
b10100000000000000000000 E
1#
#1110
0#
#1115
b101000000000000000000000 E
b10 D
1#
#1120
0#
#1125
b1001 A
1#
#1130
0#
#1135
b1010 A
1#
#1140
0#
#1145
b1011 A
1#
#1150
0#
#1155
b1100 A
b1000000101000000000000000000000 C
1#
#1160
0#
#1165
b1000000101000000000000000000000 "
b1000000101000000000000000000000 ,
b1000000101000000000000000000000 H
b1000000101000000000000000000000 2
b1000000101000000000000000000000 @
b1000000101000000000000000000000 G
1!
1I
11
1#
